pidgan/__init__.py
pidgan/version.py
pidgan/algorithms/ProjectedGAN.py
pidgan/algorithms/__init__.py
pidgan/algorithms/k2/BceGAN.py
pidgan/algorithms/k2/BceGAN_ALP.py
pidgan/algorithms/k2/BceGAN_GP.py
pidgan/algorithms/k2/CramerGAN.py
pidgan/algorithms/k2/GAN.py
pidgan/algorithms/k2/LSGAN.py
pidgan/algorithms/k2/WGAN.py
pidgan/algorithms/k2/WGAN_ALP.py
pidgan/algorithms/k2/WGAN_GP.py
pidgan/algorithms/k2/__init__.py
pidgan/algorithms/k2/lipschitz_regularizations.py
pidgan/algorithms/k3/BceGAN.py
pidgan/algorithms/k3/BceGAN_ALP.py
pidgan/algorithms/k3/BceGAN_GP.py
pidgan/algorithms/k3/CramerGAN.py
pidgan/algorithms/k3/GAN.py
pidgan/algorithms/k3/LSGAN.py
pidgan/algorithms/k3/WGAN.py
pidgan/algorithms/k3/WGAN_ALP.py
pidgan/algorithms/k3/WGAN_GP.py
pidgan/algorithms/k3/__init__.py
pidgan/algorithms/k3/lipschitz_regularizations.py
pidgan/callbacks/__init__.py
pidgan/callbacks/schedulers/__init__.py
pidgan/callbacks/schedulers/k2/LearnRateBaseScheduler.py
pidgan/callbacks/schedulers/k2/LearnRateCosineDecay.py
pidgan/callbacks/schedulers/k2/LearnRateExpDecay.py
pidgan/callbacks/schedulers/k2/LearnRateInvTimeDecay.py
pidgan/callbacks/schedulers/k2/LearnRatePiecewiseConstDecay.py
pidgan/callbacks/schedulers/k2/LearnRatePolynomialDecay.py
pidgan/callbacks/schedulers/k2/__init__.py
pidgan/callbacks/schedulers/k3/LearnRateBaseScheduler.py
pidgan/callbacks/schedulers/k3/LearnRateCosineDecay.py
pidgan/callbacks/schedulers/k3/LearnRateExpDecay.py
pidgan/callbacks/schedulers/k3/LearnRateInvTimeDecay.py
pidgan/callbacks/schedulers/k3/LearnRatePiecewiseConstDecay.py
pidgan/callbacks/schedulers/k3/LearnRatePolynomialDecay.py
pidgan/callbacks/schedulers/k3/__init__.py
pidgan/metrics/__init__.py
pidgan/metrics/k2/Accuracy.py
pidgan/metrics/k2/BaseMetric.py
pidgan/metrics/k2/BinaryCrossentropy.py
pidgan/metrics/k2/JSDivergence.py
pidgan/metrics/k2/KLDivergence.py
pidgan/metrics/k2/MeanAbsoluteError.py
pidgan/metrics/k2/MeanSquaredError.py
pidgan/metrics/k2/RootMeanSquaredError.py
pidgan-0.2.0.dist-info/LICENSE
pidgan-0.2.0.dist-info/METADATA
pidgan-0.2.0.dist-info/WHEEL
pidgan-0.2.0.dist-info/top_level.txt
pidgan-0.2.0.dist-info/RECORD
