Metadata-Version: 2.1
Name: pidgan
Version: 0.2.0
Summary: GAN-based models to flash-simulate the LHCb PID detectors
Author-email: Matteo Barbetti <matteo.barbetti@cnaf.infn.it>, Lucio Anderlini <lucio.anderlini@fi.infn.it>
License: GPLv3 License
Project-URL: repository, https://github.com/mbarbetti/pidgan
Keywords: tensorflow,keras,machine learning,deep learning,generative models,generative adversarial nets,lhcb experiment,lamarr,flash-simulation,particle identification
Classifier: Development Status :: 4 - Beta
Classifier: Environment :: GPU :: NVIDIA CUDA :: 11.2
Classifier: Environment :: GPU :: NVIDIA CUDA :: 11.8
Classifier: Environment :: GPU :: NVIDIA CUDA :: 12 :: 12.2
Classifier: Intended Audience :: Science/Research
Classifier: License :: OSI Approved :: GNU General Public License v3 (GPLv3)
Classifier: Programming Language :: Python :: 3.7
Classifier: Programming Language :: Python :: 3.8
Classifier: Programming Language :: Python :: 3.9
Classifier: Programming Language :: Python :: 3.11
Classifier: Programming Language :: Python :: 3.12
Classifier: Topic :: Scientific/Engineering :: Physics
Classifier: Topic :: Scientific/Engineering :: Artificial Intelligence
Requires-Python: <3.13,>=3.7
License-File: LICENSE
Requires-Dist: tensorflow <2.17,>=2.8
Requires-Dist: scikit-learn <1.6,>=1.0
Requires-Dist: numpy <2.0
Provides-Extra: hep
Requires-Dist: matplotlib <4.0,>=3.7 ; extra == 'hep'
Requires-Dist: html-reports >=0.2 ; extra == 'hep'
Requires-Dist: scikinC >=0.2.6 ; extra == 'hep'
Requires-Dist: pandas ; extra == 'hep'
Requires-Dist: uproot ; extra == 'hep'
Requires-Dist: pyyaml ; extra == 'hep'
Requires-Dist: tqdm ; extra == 'hep'
Provides-Extra: style
Requires-Dist: ruff ; extra == 'style'
Provides-Extra: tests
Requires-Dist: pytest >=6.0 ; extra == 'tests'
Requires-Dist: pytest-cov ; extra == 'tests'
Requires-Dist: pyyaml ; extra == 'tests'
